{
  "serieC": {
    "standings": [],
    "teamStats": {},
    "lastUpdate": "2025-09-18T18:08:58.358Z",
    "error": "Dati non disponibili"
  },
  "under17": {
    "standings": [],
    "teamStats": {},
    "lastUpdate": "2025-09-18T18:09:28.359Z",
    "error": "Dati non disponibili"
  },
  "under13": {
    "standings": [],
    "teamStats": {},
    "lastUpdate": "2025-09-18T18:09:58.360Z",
    "error": "Dati non disponibili"
  },
  "lastUpdate": "2025-09-18T18:08:27.115Z",
  "source": "playbasket.it"
}